Chapter 6/ModelSim/pwmdecoder.vhd
library ieee;
use ieee.std_logic_1164.all;
use ieee.std_logic_unsigned.all;
use ieee.numeric_std.all;

entity pwmdecoder is
	generic( 
		dec_clkspeed:					integer	:=	50_000_000;
		dec_pwmfrequency:			integer := 	100_000;
		dec_resolution:				integer	:=	8
	);
	port (
		dec_clk:				in 	std_logic;
		dec_rst:				in	std_logic;
		dec_pwm:				in	std_logic;
		dec_direction:	in	std_logic;
		dec_pulsewidth:	out	std_logic_vector(dec_resolution downto 0)
	);
end entity pwmdecoder;

architecture rtl of pwmdecoder is
	constant period:	integer		:=	dec_clkspeed/dec_pwmfrequency;
	signal D:					integer range 0 to period-1 := 0;
	signal start:			std_logic := '0';
begin
	process(dec_clk, dec_rst, dec_pwm) begin
		if(dec_rst = '1') then
			D <= 0;
			dec_pulsewidth <= std_logic_vector(to_unsigned(0,dec_pulsewidth'length));
		elsif rising_edge(dec_pwm) then
			D <= 0;
			start <= '1';
		elsif rising_edge(dec_clk) and (start = '1') then
			if(dec_pwm = '1') then
				D <= D + 1; --Counting number of high ticks.
			elsif(dec_pwm = '0') then
				start <= '0';
				dec_pulsewidth <= std_logic_vector(to_unsigned(D,dec_pulsewidth'length)); --Outputting number of high ticks.
			end if;
		end if;
	end process;	
end architecture rtl;

Chapter 5/Plant/pwm.vhd
library ieee;
use ieee.std_logic_1164.all;
use ieee.std_logic_unsigned.all;

entity pwm is
  generic (
    clkspeed:  integer :=  50_000_000;
    pwmfrequency:  integer :=  100_000;
    resolution: integer :=  8
  );
  port (
    clk:  in  std_logic;
    rst:  in  std_logic;
    D:    in  std_logic_vector(resolution-1 downto 0);
    adjust: in  std_logic;
    direction_in: in std_logic; --'0' = clockwise and '1' = counter-clockwise. Can be turned off by setting the duty cycle 'b00000000
    pwmout:  out std_logic;
    direction_out:  out std_logic
  );
end pwm;

architecture arch of pwm is
  constant period:  integer :=  clkspeed/pwmfrequency;
  signal counter:   integer range 0 to period-1;
  signal D_new:  integer range 0 to period/2 := 0;
  signal D_current:     integer range 0 to period/2;
begin
  process(clk, rst) begin
    if(rst = '1') then
      counter <= 0;
      pwmout <= '0';
      direction_out <= '0';
    elsif rising_edge(clk) then
      if(adjust = '1') then                 --adjust duty cycle
        D_new <= conv_integer(D) * period / (2 ** resolution)/2;
      end if;
      if(counter = period - 1) then         --end of period
        counter <= 0;
        D_current <= D_new;
        direction_out <= direction_in;
      else                                  --not end of period
        counter <= counter + 1;
      end if;
      if(counter = D_current) then              --phase falling edge reached
        pwmout <= '0';
      elsif(counter = period - D_current) then  --phase rising edge reached
        pwmout <= '1';
      end if;
    end if;
  end process;
end arch;

Chapter3/VHDL/PWMdecoder/pwmdecoder_tb.vhd
library ieee;
use ieee.std_logic_1164.all;
use ieee.std_logic_unsigned.all;
use ieee.numeric_std.all;

entity pwmdecoder_tb is
end pwmdecoder_tb;

architecture testbench of pwmdecoder_tb is
  component pwm
    generic (
      clkspeed:  integer :=  50_000_000;
      pwmfrequency:  integer :=  100_000;
      resolution: integer :=  8
    );
    port (
      clk:  in  std_logic;
      rst:  in  std_logic;
      D:    in  std_logic_vector(resolution-1 downto 0);
      adjust: in  std_logic;
      direction_in: in std_logic; --'0' = clockwise and '1' = counter-clockwise. Can be turned off by setting the duty cycle 'b00000000
      pwmout:  out std_logic;
      direction_out:  out std_logic
    );
  end component;

  component pwmdecoder
    generic( 
      dec_clkspeed:					integer	:=	50_000_000;
      dec_pwmfrequency:			integer := 	100_000;
      dec_resolution:				integer	:=	8
    );
    port (
      dec_clk:				in 	std_logic;
      dec_rst:				in	std_logic;
      dec_pwm:				in	std_logic;
      dec_direction:	in	std_logic;
      dec_pulsewidth:	out	std_logic_vector(dec_resolution downto 0)
      );
  end component;

  signal clk:             std_logic                     := '0';
  signal rst:             std_logic                     := '1';
  signal adjust:          std_logic                     := '1';
  signal D:               std_logic_vector(7 downto 0)  := "10000000";
  signal direction:       std_logic                     := '0';
  signal pwmconnect:      std_logic;
  signal dec_resolution:  integer                       := 8;
  signal dec_pulsewidth:  std_logic_vector(dec_resolution downto 0);

begin
  u0 : pwm port map(clk => clk, rst => rst, D => D, adjust => adjust, direction_in => direction, pwmout => pwmconnect);
  u1 : pwmdecoder port map(dec_clk => clk, dec_rst => rst, dec_pwm => pwmconnect, dec_direction => direction, dec_pulsewidth => dec_pulsewidth);

  process begin
    wait for 10 ns;
		rst <= '0';
    wait for 10 ns;
    
    for I in 0 to 10000 loop
      clk <= '0';
      wait for 10 ns;
      clk <= '1';
      wait for 10 ns;
    end loop;

    D <= "11111100";

    for I in 0 to 10000 loop
      clk <= '0';
      wait for 10 ns;
      clk <= '1';
      wait for 10 ns;
    end loop;

    D <= "11100000";

    for I in 0 to 10000 loop
      clk <= '0';
      wait for 10 ns;
      clk <= '1';
      wait for 10 ns;
    end loop;

    D <= "11111111";

    for I in 0 to 10000 loop
      clk <= '0';
      wait for 10 ns;
      clk <= '1';
      wait for 10 ns;
    end loop;

    assert false report "End of test";
    wait;
  end process;
end architecture testbench;

Chapter3/VHDL/PWMdecoder/pwmdecoder.vcd
$date
  Tue May 19 14:54:18 2020
$end
$version
  GHDL v0
$end
$timescale
  1 fs
$end
$scope module standard $end
$upscope $end
$scope module std_logic_1164 $end
$upscope $end
$scope module std_logic_arith $end
$upscope $end
$scope module std_logic_unsigned $end
$upscope $end
$scope module numeric_std $end
$upscope $end
$scope module pwmdecoder_tb $end
$var reg 1 ! clk $end
$var reg 1 " rst $end
$var reg 1 # adjust $end
$var reg 8 $ d[7:0] $end
$var reg 1 % direction $end
$var reg 1 & pwmconnect $end
$var integer 32 ' dec_resolution $end
$var reg 9 ( dec_pulsewidth[8:0] $end
$scope module u0 $end
$var reg 1 ) clk $end
$var reg 1 * rst $end
$var reg 8 + d[7:0] $end
$var reg 1 , adjust $end
$var reg 1 - direction_in $end
$var reg 1 . pwmout $end
$var reg 1 / direction_out $end
$var integer 32 0 counter $end
$var integer 32 1 d_new $end
$var integer 32 2 d_current $end
$upscope $end
$scope module u1 $end
$var reg 1 3 dec_clk $end
$var reg 1 4 dec_rst $end
$var reg 1 5 dec_pwm $end
$var reg 1 6 dec_direction $end
$var reg 9 7 dec_pulsewidth[8:0] $end
$var integer 32 8 d $end
$var reg 1 9 start $end
$upscope $end
$upscope $end
$enddefinitions $end
#0
0!
1"
1#
b10000000 $
0%
0&
b1000 '
b000000000 (
0)
1*
b10000000 +
1,
0-
0.
0/
b0 0
b0 1
b0 2
03
14
05
06
b000000000 7
b0 8
09
#10000000
0"
0*
04
#20000000
#30000000
1!
1)
b1 0
b1111101 1
13
#40000000
0!
0)
03
#50000000
1!
1)
b10 0
13
#60000000
0!
0)
03
#70000000
1!
1)
b11 0
13
#80000000
0!
0)
03
#90000000
1!
1)
b100 0
13
#100000000
0!
0)
03
#110000000
1!
1)
b101 0
13
#120000000
0!
0)
03
#130000000
1!
1)
b110 0
13
#140000000
0!
0)
03
#150000000
1!
1)
b111 0
13
#160000000
0!
0)
03
#170000000
1!
1)
b1000 0
13
#180000000
0!
0)
03
#190000000
1!
1)
b1001 0
13
#200000000
0!
0)
03
#210000000
1!
1)
b1010 0
13
#220000000
0!
0)
03
#230000000
1!
1)
b1011 0
13
#240000000
0!
0)
03
#250000000
1!
1)
b1100 0
13
#260000000
0!
0)
03
#270000000
1!
1)
b1101 0
13
#280000000
0!
0)
03
#290000000
1!
1)
b1110 0
13
#300000000
0!
0)
03
#310000000
1!
1)
b1111 0
13
#320000000
0!
0)
03
#330000000
1!
1)
b10000 0
13
#340000000
0!
0)
03
#350000000
1!
1)
b10001 0
13
#360000000
0!
0)
03
#370000000
1!
1)
b10010 0
13
#380000000
0!
0)
03
#390000000
1!
1)
b10011 0
13
#400000000
0!
0)
03
#410000000
1!
1)
b10100 0
13
#420000000
0!
0)
03
#430000000
1!
1)
b10101 0
13
#440000000
0!
0)
03
#450000000
1!
1)
b10110 0
13
#460000000
0!
0)
03
#470000000
1!
1)
b10111 0
13
#480000000
0!
0)
03
#490000000
1!
1)
b11000 0
13
#500000000
0!
0)
03
#510000000
1!
1)
b11001 0
13
#520000000
0!
0)
03
#530000000
1!
1)
b11010 0
13
#540000000
0!
0)
03
#550000000
1!
1)
b11011 0
13
#560000000
0!
0)
03
#570000000
1!
1)
b11100 0
13
#580000000
0!
0)
03
#590000000
1!
1)
b11101 0
13
#600000000
0!
0)
03
#610000000
1!
1)
b11110 0
13
#620000000
0!
0)
03
#630000000
1!
1)
b11111 0
13
#640000000
0!
0)
03
#650000000
1!
1)
b100000 0
13
#660000000
0!
0)
03
#670000000
1!
1)
b100001 0
13
#680000000
0!
0)
03
#690000000
1!
1)
b100010 0
13
#700000000
0!
0)
03
#710000000
1!
1)
b100011 0
13
#720000000
0!
0)
03
#730000000
1!
1)
b100100 0
13
#740000000
0!
0)
03
#750000000
1!
1)
b100101 0
13
#760000000
0!
0)
03
#770000000
1!
1)
b100110 0
13
#780000000
0!
0)
03
#790000000
1!
1)
b100111 0
13
#800000000
0!
0)
03
#810000000
1!
1)
b101000 0
13
#820000000
0!
0)
03
#830000000
1!
1)
b101001 0
13
#840000000
0!
0)
03
#850000000
1!
1)
b101010 0
13
#860000000
0!
0)
03
#870000000
1!
1)
b101011 0
13
#880000000
0!
0)
03
#890000000
1!
1)
b101100 0
13
#900000000
0!
0)
03
#910000000
1!
1)
b101101 0
13
#920000000
0!
0)
03
#930000000
1!
1)
b101110 0
13
#940000000
0!
0)
03
#950000000
1!
1)
b101111 0
13
#960000000
0!
0)
03
#970000000
1!
1)
b110000 0
13
#980000000
0!
0)
03
#990000000
1!
1)
b110001 0
13
#1000000000
0!
0)
03
#1010000000
1!
1)
b110010 0
13
#1020000000
0!
0)
03
#1030000000
1!
1)
b110011 0
13
#1040000000
0!
0)
03
#1050000000
1!
1)
b110100 0
13
#1060000000
0!
0)
03
#1070000000
1!
1)
b110101 0
13
#1080000000
0!
0)
03
#1090000000
1!
1)
b110110 0
13
#1100000000
0!
0)
03
#1110000000
1!
1)
b110111 0
13
#1120000000
0!
0)
03
#1130000000
1!
1)
b111000 0
13
#1140000000
0!
0)
03
#1150000000
1!
1)
b111001 0
13
#1160000000
0!
0)
03
#1170000000
1!
1)
b111010 0
13
#1180000000
0!
0)
03
#1190000000
1!
1)
b111011 0
13
#1200000000
0!
0)
03
#1210000000
1!
1)
b111100 0
13
#1220000000
0!
0)
03
#1230000000
1!
1)
b111101 0
13
#1240000000
0!
0)
03
#1250000000
1!
1)
b111110 0
13
#1260000000
0!
0)
03
#1270000000
1!
1)
b111111 0
13
#1280000000
0!
0)
03
#1290000000
1!
1)
b1000000 0
13
#1300000000
0!
0)
03
#1310000000
1!
1)
b1000001 0
13
#1320000000
0!
0)
03
#1330000000
1!
1)
b1000010 0
13
#1340000000
0!
0)
03
#1350000000
1!
1)
b1000011 0
13
#1360000000
0!
0)
03
#1370000000
1!
1)
b1000100 0
13
#1380000000
0!
0)
03
#1390000000
1!
1)
b1000101 0
13
#1400000000
0!
0)
03
#1410000000
1!
1)
b1000110 0
13
#1420000000
0!
0)
03
#1430000000
1!
1)
b1000111 0
13
#1440000000
0!
0)
03
#1450000000
1!
1)
b1001000 0
13
#1460000000
0!
0)
03
#1470000000
1!
1)
b1001001 0
13
#1480000000
0!
0)
03
#1490000000
1!
1)
b1001010 0
13
#1500000000
0!
0)
03
#1510000000
1!
1)
b1001011 0
13
#1520000000
0!
0)
03
#1530000000
1!
1)
b1001100 0
13
#1540000000
0!
0)
03
#1550000000
1!
1)
b1001101 0
13
#1560000000
0!
0)
03
#1570000000
1!
1)
b1001110 0
13
#1580000000
0!
0)
03
#1590000000
1!
1)
b1001111 0
13
#1600000000
0!
0)
03
#1610000000
1!
1)
b1010000 0
13
#1620000000
0!
0)
03
#1630000000
1!
1)
b1010001 0
13
#1640000000
0!
0)
03
#1650000000
1!
1)
b1010010 0
13
#1660000000
0!
0)
03
#1670000000
1!
1)
b1010011 0
13
#1680000000
0!
0)
03
#1690000000
1!
1)
b1010100 0
13
#1700000000
0!
0)
03
#1710000000
1!
1)
b1010101 0
13
#1720000000
0!
0)
03
#1730000000
1!
1)
b1010110 0
13
#1740000000
0!
0)
03
#1750000000
1!
1)
b1010111 0
13
#1760000000
0!
0)
03
#1770000000
1!
1)
b1011000 0
13
#1780000000
0!
0)
03
#1790000000
1!
1)
b1011001 0
13
#1800000000
0!
0)
03
#1810000000
1!
1)
b1011010 0
13
#1820000000
0!
0)
03
#1830000000
1!
1)
b1011011 0
13
#1840000000
0!
0)
03
#1850000000
1!
1)
b1011100 0
13
#1860000000
0!
0)
03
#1870000000
1!
1)
b1011101 0
13
#1880000000
0!
0)
03
#1890000000
1!
1)
b1011110 0
13
#1900000000
0!
0)
03
#1910000000
1!
1)
b1011111 0
13
#1920000000
0!
0)
03
#1930000000
1!
1)
b1100000 0
13
#1940000000
0!
0)
03
#1950000000
1!
1)
b1100001 0
13
#1960000000
0!
0)
03
#1970000000
1!
1)
b1100010 0
13
#1980000000
0!
0)
03
#1990000000
1!
1)
b1100011 0
13
#2000000000
0!
0)
03
#2010000000
1!
1)
b1100100 0
13
#2020000000
0!
0)
03
#2030000000
1!
1)
b1100101 0
13
#2040000000
0!
0)
03
#2050000000
1!
1)
b1100110 0
13
#2060000000
0!
0)
03
#2070000000
1!
1)
b1100111 0
13
#2080000000
0!
0)
03
#2090000000
1!
1)
b1101000 0
13
#2100000000
0!
0)
03
#2110000000
1!
1)
b1101001 0
13
#2120000000
0!
0)
03
#2130000000
1!
1)
b1101010 0
13
#2140000000
0!
0)
03
#2150000000
1!
1)
b1101011 0
13
#2160000000
0!
0)
03
#2170000000
1!
1)
b1101100 0
13
#2180000000
0!
0)
03
#2190000000
1!
1)
b1101101 0
13
#2200000000
0!
0)
03
#2210000000
1!
1)
b1101110 0
13
#2220000000
0!
0)
03
#2230000000
1!
1)
b1101111 0
13
#2240000000
0!
0)
03
#2250000000
1!
1)
b1110000 0
13
#2260000000
0!
0)
03
#2270000000
1!
1)
b1110001 0
13
#2280000000
0!
0)
03
#2290000000
1!
1)
b1110010 0
13
#2300000000
0!
0)
03
#2310000000
1!
1)
b1110011 0
13
#2320000000
0!
0)
03
#2330000000
1!
1)
b1110100 0
13
#2340000000
0!
0)
03
#2350000000
1!
1)
b1110101 0
13
#2360000000
0!
0)
03
#2370000000
1!
1)
b1110110 0
13
#2380000000
0!
0)
03
#2390000000
1!
1)
b1110111 0
13
#2400000000
0!
0)
03
#2410000000
1!
1)
b1111000 0
13
#2420000000
0!
0)
03
#2430000000
1!
1)
b1111001 0
13
#2440000000
0!
0)
03
#2450000000
1!
1)
b1111010 0
13
#2460000000
0!
0)
03
#2470000000
1!
1)
b1111011 0
13
#2480000000
0!
0)
03
#2490000000
1!
1)
b1111100 0
13
#2500000000
0!
0)
03
#2510000000
1!
1)
b1111101 0
13
#2520000000
0!
0)
03
#2530000000
1!
1)
b1111110 0
13
#2540000000
0!
0)
03
#2550000000
1!
1)
b1111111 0
13
#2560000000
0!
0)
03
#2570000000
1!
1)
b10000000 0
13
#2580000000
0!
0)
03
#2590000000
1!
1)
b10000001 0
13
#2600000000
0!
0)
03
#2610000000
1!
1)
b10000010 0
13
#2620000000
0!
0)
03
#2630000000
1!
1)
b10000011 0
13
#2640000000
0!
0)
03
#2650000000
1!
1)
b10000100 0
13
#2660000000
0!
0)
03
#2670000000
1!
1)
b10000101 0
13
#2680000000
0!
0)
03
#2690000000
1!
1)
b10000110 0
13
#2700000000
0!
0)
03
#2710000000
1!
1)
b10000111 0
13
#2720000000
0!
0)
03
#2730000000
1!
1)
b10001000 0
13
#2740000000
0!
0)
03
#2750000000
1!
1)
b10001001 0
13
#2760000000
0!
0)
03
#2770000000
1!
1)
b10001010 0
13
#2780000000
0!
0)
03
#2790000000
1!
1)
b10001011 0
13
#2800000000
0!
0)
03
#2810000000
1!
1)
b10001100 0
13
#2820000000
0!
0)
03
#2830000000
1!
1)
b10001101 0
13
#2840000000
0!
0)
03
#2850000000
1!
1)
b10001110 0
13
#2860000000
0!
0)
03
#2870000000
1!
1)
b10001111 0
13
#2880000000
0!
0)
03
#2890000000
1!
1)
b10010000 0
13
#2900000000
0!
0)
03
#2910000000
1!
1)
b10010001 0
13
#2920000000
0!
0)
03
#2930000000
1!
1)
b10010010 0
13
#2940000000
0!
0)
03
#2950000000
1!
1)
b10010011 0
13
#2960000000
0!
0)
03
#2970000000
1!
1)
b10010100 0
13
#2980000000
0!
0)
03
#2990000000
1!
1)
b10010101 0
13
#3000000000
0!
0)
03
#3010000000
1!
1)
b10010110 0
13
#3020000000
0!
0)
03
#3030000000
1!
1)
b10010111 0
13
#3040000000
0!
0)
03
#3050000000
1!
1)
b10011000 0
13
#3060000000
0!
0)
03
#3070000000
1!
1)
b10011001 0
13
#3080000000
0!
0)
03
#3090000000
1!
1)
b10011010 0
13
#3100000000
0!
0)
03
#3110000000
1!
1)
b10011011 0
13
#3120000000
0!
0)
03
#3130000000
1!
1)
b10011100 0
13
#3140000000
0!
0)
03
#3150000000
1!
1)
b10011101 0
13
#3160000000
0!
0)
03
#3170000000
1!
1)
b10011110 0
13
#3180000000
0!
0)
03
#3190000000
1!
1)
b10011111 0
13
#3200000000
0!
0)
03
#3210000000
1!
1)
b10100000 0
13
#3220000000
0!
0)
03
#3230000000
1!
1)
b10100001 0
13
#3240000000
0!
0)
03
#3250000000
1!
1)
b10100010 0
13
#3260000000
0!
0)
03
#3270000000
1!
1)
b10100011 0
13
#3280000000
0!
0)
03
#3290000000
1!
1)
b10100100 0
13
#3300000000
0!
0)
03
#3310000000
1!
1)
b10100101 0
13
#3320000000
0!
0)
03
#3330000000
1!
1)
b10100110 0
13
#3340000000
0!
0)
03
#3350000000
1!
1)
b10100111 0
13
#3360000000
0!
0)
03
#3370000000
1!
1)
b10101000 0
13
#3380000000
0!
0)
03
#3390000000
1!
1)
b10101001 0
13
#3400000000
0!
0)
03
#3410000000
1!
1)
b10101010 0
13
#3420000000
0!
0)
03
#3430000000
1!
1)
b10101011 0
13
#3440000000
0!
0)
03
#3450000000
1!
1)
b10101100 0
13
#3460000000
0!
0)
03
#3470000000
1!
1)
b10101101 0
13
#3480000000
0!
0)
03
#3490000000
1!
1)
b10101110 0
13
#3500000000
0!
0)
03
#3510000000
1!
1)
b10101111 0
13
#3520000000
0!
0)
03
#3530000000
1!
1)
b10110000 0
13
#3540000000
0!
0)
03
#3550000000
1!
1)
b10110001 0
13
#3560000000
0!
0)
03
#3570000000
1!
1)
b10110010 0
13
#3580000000
0!
0)
03
#3590000000
1!
1)
b10110011 0
13
#3600000000
0!
0)
03
#3610000000
1!
1)
b10110100 0
13
#3620000000
0!
0)
03
#3630000000
1!
1)
b10110101 0
13
#3640000000
0!
0)
03
#3650000000
1!
1)
b10110110 0
13
#3660000000
0!
0)
03
#3670000000
1!
1)
b10110111 0
13
#3680000000
0!
0)
03
#3690000000
1!
1)
b10111000 0
13
#3700000000
0!
0)
03
#3710000000
1!
1)
b10111001 0
13
#3720000000
0!
0)
03
#3730000000
1!
1)
b10111010 0
13
#3740000000
0!
0)
03
#3750000000
1!
1)
b10111011 0
13
#3760000000
0!
0)
03
#3770000000
1!
1)
b10111100 0
13
#3780000000
0!
0)
03
#3790000000
1!
1)
b10111101 0
13
#3800000000
0!
0)
03
#3810000000
1!
1)
b10111110 0
13
#3820000000
0!
0)
03
#3830000000
1!
1)
b10111111 0
13
#3840000000
0!
0)
03
#3850000000
1!
1)
b11000000 0
13
#3860000000
0!
0)
03
#3870000000
1!
1)
b11000001 0
13
#3880000000
0!
0)
03
#3890000000
1!
1)
b11000010 0
13
#3900000000
0!
0)
03
#3910000000
1!
1)
b11000011 0
13
#3920000000
0!
0)
03
#3930000000
1!
1)
b11000100 0
13
#3940000000
0!
0)
03
#3950000000
1!
1)
b11000101 0
13
#3960000000
0!
0)
03
#3970000000
1!
1)
b11000110 0
13
#3980000000
0!
0)
03
#3990000000
1!
1)
b11000111 0
13
#4000000000
0!
0)
03
#4010000000
1!
1)
b11001000 0
13
#4020000000
0!
0)
03
#4030000000
1!
1)
b11001001 0
13
#4040000000
0!
0)
03
#4050000000
1!
1)
b11001010 0
13
#4060000000
0!
0)
03
#4070000000
1!
1)
b11001011 0
13
#4080000000
0!
0)
03
#4090000000
1!
1)
b11001100 0
13
#4100000000
0!
0)
03
#4110000000
1!
1)
b11001101 0
13
#4120000000
0!
0)
03
#4130000000
1!
1)
b11001110 0
13
#4140000000
0!
0)
03
#4150000000
1!
1)
b11001111 0
13
#4160000000
0!
0)
03
#4170000000
1!
1)
b11010000 0
13
#4180000000
0!
0)
03
#4190000000
1!
1)
b11010001 0
13
#4200000000
0!
0)
03
#4210000000
1!
1)
b11010010 0
13
#4220000000
0!
0)
03
#4230000000
1!
1)
b11010011 0
13
#4240000000
0!
0)
03
#4250000000
1!
1)
b11010100 0
13
#4260000000
0!
0)
03
#4270000000
1!
1)
b11010101 0
13
#4280000000
0!
0)
03
#4290000000
1!
1)
b11010110 0
13
#4300000000
0!
0)
03
#4310000000
1!
1)
b11010111 0
13
#4320000000
0!
0)
03
#4330000000
1!
1)
b11011000 0
13
#4340000000
0!
0)
03
#4350000000
1!
1)
b11011001 0
13
#4360000000
0!
0)
03
#4370000000
1!
1)
b11011010 0
13
#4380000000
0!
0)
03
#4390000000
1!
1)
b11011011 0
13
#4400000000
0!
0)
03
#4410000000
1!
1)
b11011100 0
13
#4420000000
0!
0)
03
#4430000000
1!
1)
b11011101 0
13
#4440000000
0!
0)
03
#4450000000
1!
1)
b11011110 0
13
#4460000000
0!
0)
03
#4470000000
1!
1)
b11011111 0
13
#4480000000
0!
0)
03
#4490000000
1!
1)
b11100000 0
13
#4500000000
0!
0)
03
#4510000000
1!
1)
b11100001 0
13
#4520000000
0!
0)
03
#4530000000
1!
1)
b11100010 0
13
#4540000000
0!
0)
03
#4550000000
1!
1)
b11100011 0
13
#4560000000
0!
0)
03
#4570000000
1!
1)
b11100100 0
13
#4580000000
0!
0)
03
#4590000000
1!
1)
b11100101 0
13
#4600000000
0!
0)
03
#4610000000
1!
1)
b11100110 0
13
#4620000000
0!
0)
03
#4630000000
1!
1)
b11100111 0
13
#4640000000
0!
0)
03
#4650000000
1!
1)
b11101000 0
13
#4660000000
0!
0)
03
#4670000000
1!
1)
b11101001 0
13
#4680000000
0!
0)
03
#4690000000
1!
1)
b11101010 0
13
#4700000000
0!
0)
03
#4710000000
1!
1)
b11101011 0
13
#4720000000
0!
0)
03
#4730000000
1!
1)
b11101100 0
13
#4740000000
0!
0)
03
#4750000000
1!
1)
b11101101 0
13
#4760000000
0!
0)
03
#4770000000
1!
1)
b11101110 0
13
#4780000000
0!
0)
03
#4790000000
1!
1)
b11101111 0
13
#4800000000
0!
0)
03
#4810000000
1!
1)
b11110000 0
13
#4820000000
0!
0)
03
#4830000000
1!
1)
b11110001 0
13
#4840000000
0!
0)
03
#4850000000
1!
1)
b11110010 0
13
#4860000000
0!
0)
03
#4870000000
1!
1)
b11110011 0
13
#4880000000
0!
0)
03
#4890000000
1!
1)
b11110100 0
13
#4900000000
0!
0)
03
#4910000000
1!
1)
b11110101 0
13
#4920000000
0!
0)
03
#4930000000
1!
1)
b11110110 0
13
#4940000000
0!
0)
03
#4950000000
1!
1)
b11110111 0
13
#4960000000
0!
0)
03
#4970000000
1!
1)
b11111000 0
13
#4980000000
0!
0)
03
#4990000000
1!
1)
b11111001 0
13
#5000000000
0!
0)
03
#5010000000
1!
1)
b11111010 0
13
#5020000000
0!
0)
03
#5030000000
1!
1)
b11111011 0
13
#5040000000
0!
0)
03
#5050000000
1!
1)
b11111100 0
13
#5060000000
0!
0)
03
#5070000000
1!
1)
b11111101 0
13
#5080000000
0!
0)
03
#5090000000
1!
1)
b11111110 0
13
#5100000000
0!
0)
03
#5110000000
1!
1)
b11111111 0
13
#5120000000
0!
0)
03
#5130000000
1!
1)
b100000000 0
13
#5140000000
0!
0)
03
#5150000000
1!
1)
b100000001 0
13
#5160000000
0!
0)
03
#5170000000
1!
1)
b100000010 0
13
#5180000000
0!
0)
03
#5190000000
1!
1)
b100000011 0
13
#5200000000
0!
0)
03
#5210000000
1!
1)
b100000100 0
13
#5220000000
0!
0)
03
#5230000000
1!
1)
b100000101 0
13
#5240000000
0!
0)
03
#5250000000
1!
1)
b100000110 0
13
#5260000000
0!
0)
03
#5270000000
1!
1)
b100000111 0
13
#5280000000
0!
0)
03
#5290000000
1!
1)
b100001000 0
13
#5300000000
0!
0)
03
#5310000000
1!
1)
b100001001 0
13
#5320000000
0!
0)
03
#5330000000
1!
1)
b100001010 0
13
#5340000000
0!
0)
03
#5350000000
1!
1)
b100001011 0
13
#5360000000
0!
0)
03
#5370000000
1!
1)
b100001100 0
13
#5380000000
0!
0)
03
#5390000000
1!
1)
b100001101 0
13
#5400000000
0!
0)
03
#5410000000
1!
1)
b100001110 0
13
#5420000000
0!
0)
03
#5430000000
1!
1)
b100001111 0
13
#5440000000
0!
0)
03
#5450000000
1!
1)
b100010000 0
13
#5460000000
0!
0)
03
#5470000000
1!
1)
b100010001 0
13
#5480000000
0!
0)
03
#5490000000
1!
1)
b100010010 0
13
#5500000000
0!
0)
03
#5510000000
1!
1)
b100010011 0
13
#5520000000
0!
0)
03
#5530000000
1!
1)
b100010100 0
13
#5540000000
0!
0)
03
#5550000000
1!
1)
b100010101 0
13
#5560000000
0!
0)
03
#5570000000
1!
1)
b100010110 0
13
#5580000000
0!
0)
03
#5590000000
1!
1)
b100010111 0
13
#5600000000
0!
0)
03
#5610000000
1!
1)
b100011000 0
13
#5620000000
0!
0)
03
#5630000000
1!
1)
b100011001 0
13
#5640000000
0!
0)
03
#5650000000
1!
1)
b100011010 0
13
#5660000000
0!
0)
03
#5670000000
1!
1)
b100011011 0
13
#5680000000
0!
0)
03
#5690000000
1!
1)
b100011100 0
13
#5700000000
0!
0)
03
#5710000000
1!
1)
b100011101 0
13
#5720000000
0!
0)
03
#5730000000
1!
1)
b100011110 0
13
#5740000000
0!
0)
03
#5750000000
1!
1)
b100011111 0
13
#5760000000
0!
0)
03
#5770000000
1!
1)
b100100000 0
13
#5780000000
0!
0)
03
#5790000000
1!
1)
b100100001 0
13
#5800000000
0!
0)
03
#5810000000
1!
1)
b100100010 0
13
#5820000000
0!
0)
03
#5830000000
1!
1)
b100100011 0
13
#5840000000
0!
0)
03
#5850000000
1!
1)
b100100100 0
13
#5860000000
0!
0)
03
#5870000000
1!
1)
b100100101 0
13
#5880000000
0!
0)
03
#5890000000
1!
1)
b100100110 0
13
#5900000000
0!
0)
03
#5910000000
1!
1)
b100100111 0
13
#5920000000
0!
0)
03
#5930000000
1!
1)
b100101000 0
13
#5940000000
0!
0)
03
#5950000000
1!
1)
b100101001 0
13
#5960000000
0!
0)
03
#5970000000
1!
1)
b100101010 0
13
#5980000000
0!
0)
03
#5990000000
1!
1)
b100101011 0
13
#6000000000
0!
0)
03
#6010000000
1!
1)
b100101100 0
13
#6020000000
0!
0)
03
#6030000000
1!
1)
b100101101 0
13
#6040000000
0!
0)
03
#6050000000
1!
1)
b100101110 0
13
#6060000000
0!
0)
03
#6070000000
1!
1)
b100101111 0
13
#6080000000
0!
0)
03
#6090000000
1!
1)
b100110000 0
13
#6100000000
0!
0)
03
#6110000000
1!
1)
b100110001 0
13
#6120000000
0!
0)
03
#6130000000
1!
1)
b100110010 0
13
#6140000000
0!
0)
03
#6150000000
1!
1)
b100110011 0
13
#6160000000
0!
0)
03
#6170000000
1!
1)
b100110100 0
13
#6180000000
0!
0)
03
#6190000000
1!
1)
b100110101 0
13
#6200000000
0!
0)
03
#6210000000
1!
1)
b100110110 0
13
#6220000000
0!
0)
03
#6230000000
1!
1)
b100110111 0
13
#6240000000
0!
0)
03
#6250000000
1!
1)
b100111000 0
13
#6260000000
0!
0)
03
#6270000000
1!
1)
b100111001 0
13
#6280000000
0!
0)
03
#6290000000
1!
1)
b100111010 0
13
#6300000000
0!
0)
03
#6310000000
1!
1)
b100111011 0
13
#6320000000
0!
0)
03
#6330000000
1!
1)
b100111100 0
13
#6340000000
0!
0)
03
#6350000000
1!
1)
b100111101 0
13
#6360000000
0!
0)
03
#6370000000
1!
1)
b100111110 0
13
#6380000000
0!
0)
03
#6390000000
1!
1)
b100111111 0
13
#6400000000
0!
0)
03
#6410000000
1!
1)
b101000000 0
13
#6420000000
0!
0)
03
#6430000000
1!
1)
b101000001 0
13
#6440000000
0!
0)
03
#6450000000
1!
1)
b101000010 0
13
#6460000000
0!
0)
03
#6470000000
1!
1)
b101000011 0
13
#6480000000
0!
0)
03
#6490000000
1!
1)
b101000100 0
13
#6500000000
0!
0)
03
#6510000000
1!
1)
b101000101 0
13
#6520000000
0!
0)
03
#6530000000
1!
1)
b101000110 0
13
#6540000000
0!
0)
03
#6550000000
1!
1)
b101000111 0
13
#6560000000
0!
0)
03
#6570000000
1!
1)
b101001000 0
13
#6580000000
0!
0)
03
#6590000000
1!
1)
b101001001 0
13
#6600000000
0!
0)
03
#6610000000
1!
1)
b101001010 0
13
#6620000000
0!
0)
03
#6630000000
1!
1)
b101001011 0
13
#6640000000
0!
0)
03
#6650000000
1!
1)
b101001100 0
13
#6660000000
0!
0)
03
#6670000000
1!
1)
b101001101 0
13
#6680000000
0!
0)
03
#6690000000
1!
1)
b101001110 0
13
#6700000000
0!
0)
03
#6710000000
1!
1)
b101001111 0
13
#6720000000
0!
0)
03
#6730000000
1!
1)
b101010000 0
13
#6740000000
0!
0)
03
#6750000000
1!
1)
b101010001 0
13
#6760000000
0!
0)
03
#6770000000
1!
1)
b101010010 0
13
#6780000000
0!
0)
03
